{
  "type": "minecraft:crafting_shaped",
  "category": "misc",
  "group": "exotek",
  "key": {
    "C": {
      "item": "exotek:primitive_circuit_item"
    },
    "c": {
      "item": "exotek:steel_casing_block"
    },
    "g": {
      "tag": "forge:gears/steel"
    },
    "p": {
      "tag": "forge:plates/steel"
    },
    "r": {
      "tag": "forge:dusts/redstone"
    }
  },
  "pattern": [
    "pCp",
    "rcr",
    "pgp"
  ],
  "result": {
    "item": "exotek:macerator_block"
  },
  "show_notification": true
}